pvo/__init__.py
pvo/exceptions.py
pvo/models.py
pvo/pvoutput.py
pvo/py.typed
pvo-2.2.1.dist-info/METADATA
pvo-2.2.1.dist-info/WHEEL
pvo-2.2.1.dist-info/RECORD
